pyln/spec/bolt7/__init__.py
pyln/spec/bolt7/bolt.py
pyln/spec/bolt7/csv.py
pyln/spec/bolt7/gen_csv_version.py
pyln/spec/bolt7/gen_version.py
pyln/spec/bolt7/text.py
pyln_bolt7-1.0.186.post0.dist-info/WHEEL
pyln_bolt7-1.0.186.post0.dist-info/METADATA
pyln_bolt7-1.0.186.post0.dist-info/RECORD
