Metadata-Version: 2.1
Name: pyln-bolt7
Version: 1.0.186.post0
Summary: BOLT7
License: BSD-MIT
Author: Rusty Russell
Requires-Python: >=3.7,<4.0
Classifier: License :: Other/Proprietary License
Classifier: Programming Language :: Python :: 3
Classifier: Programming Language :: Python :: 3.10
Classifier: Programming Language :: Python :: 3.7
Classifier: Programming Language :: Python :: 3.8
Classifier: Programming Language :: Python :: 3.9
